{
    "webServer": "Apache",
    "appPath": "text-align/",
    "apiServer": "http://localhost/text-align-api",
    "databaseName": "alignment_db",
    "databaseLabel": "Sequence Alignment",
    "sourceDB": {
        "philoDB": false,
        "link": ""
    },
    "targetDB": {
        "philoDB": false,
        "link": ""
    },
    "metadataTypes": {
        "source_author": "text",
        "source_title": "text",
        "source_year": "integer",
        "target_author": "text",
        "target_title": "text",
        "target_year": "integer"
    },
    "sourceCitation": [
        {
            "field": "source_author",
            "style": {}
        },
        {
            "field": "source_title",
            "style": {}
        },
        {
            "field": "source_year",
            "style": {}
        }
    ],
    "targetCitation": [
        {
            "field": "target_author",
            "style": {}
        },
        {
            "field": "target_title",
            "style": { "font-style": "italic" }
        },
        {
            "field": "target_year",
            "style": {}
        }
    ],
    "metadataFields": {
        "source": [
            {
                "label": "Author",
                "value": "source_author"
            },
            {
                "label": "Title",
                "value": "source_title"
            },
            {
                "label": "Year",
                "value": "source_year"
            }
        ],
        "target": [
            {
                "label": "Author",
                "value": "target_author"
            },
            {
                "label": "Title",
                "value": "target_title"
            },
            {
                "label": "Year",
                "value": "target_year"
            }
        ]
    },
    "facetsFields": {
        "source": [
            {
                "label": "Author",
                "value": "source_author"
            },
            {
                "label": "Title",
                "value": "source_title"
            },
            {
                "label": "Year",
                "value": "source_year"
            }
        ],
        "target": [
            {
                "label": "Author",
                "value": "target_author"
            },
            {
                "label": "Title",
                "value": "target_title"
            },
            {
                "label": "Year",
                "value": "target_year"
            }
        ]
    },
    "timeSeriesIntervals": [
        {
            "label": "Year",
            "value": 1
        },
        {
            "label": "Decade",
            "value": 10
        },
        {
            "label": "Half Century",
            "value": 50
        },
        {
            "label": "Century",
            "value": 100
        }
    ]
}
